<?xml version='1.0' encoding='utf-8'?>
<!DOCTYPE hibernate-configuration PUBLIC
        "-//Hibernate/Hibernate Configuration DTD//EN"
        "http://www.hibernate.org/dtd/hibernate-configuration-3.0.dtd">
<hibernate-configuration>
    <session-factory>
        <property name="connection.url">jdbc:mysql://localhost:3306/inv_datacenter</property>
        <property name="connection.driver_class">com.mysql.jdbc.Driver</property>
        <property name="connection.username">capacityplanning</property>
        <property name="connection.password">capacityplanning</property>
        <mapping class="com.msia.cp.entities.TSMEntity"/>
        <mapping class="com.msia.cp.entities.VirtualEntity"/>
        <mapping resource="Requete_InvDatacenter.hbm.xml"/>
    </session-factory>
</hibernate-configuration>